thumbnails/__init__.py
thumbnails/__main__.py
thumbnails/cli.py
thumbnails/constants.py
thumbnails/ffmpeg.py
thumbnails/frame.py
thumbnails/generator.py
thumbnails/pathtools.py
thumbnails/progress.py
thumbnails/thumbnail.py
thumbnails/video.py
thumbnails-0.1.12.dist-info/LICENSE
thumbnails-0.1.12.dist-info/METADATA
thumbnails-0.1.12.dist-info/WHEEL
thumbnails-0.1.12.dist-info/entry_points.txt
thumbnails-0.1.12.dist-info/top_level.txt
thumbnails-0.1.12.dist-info/RECORD
