Metadata-Version: 2.1
Name: thumbnails
Version: 0.1.12
Summary: Video thumbnail generator for modern web video players such as Plyr, Videojs, Flowplayer, Fluid Player, etc.
Home-page: https://github.com/pysnippet/thumbnails
Author: Artyom Vancyan
Author-email: artyom@pysnippet.org
License: Apache 2.0
Keywords: vtt,json,plyr,video,fluid,player,videojs,thumbnail,generator,flowplayer,thumbnails,thumbnail-generator
Platform: unix
Platform: linux
Platform: osx
Platform: win32
Classifier: License :: OSI Approved :: Apache Software License
Classifier: Operating System :: OS Independent
Classifier: Programming Language :: Python :: 3
Classifier: Programming Language :: Python :: 3.7
Classifier: Programming Language :: Python :: 3.8
Classifier: Programming Language :: Python :: 3.9
Classifier: Programming Language :: Python :: 3.10
Classifier: Topic :: Multimedia :: Video
Requires-Python: >=3.8
License-File: LICENSE
Requires-Dist: av >=11.0.0
Requires-Dist: click >=8.0.3
Requires-Dist: imageio-ffmpeg >=0.4.7
Requires-Dist: imageio >=2.23.0
Requires-Dist: pillow >=8.4.0
Requires-Dist: rich ==13.0.0
Provides-Extra: testing
Requires-Dist: pytest >=6.0 ; extra == 'testing'
Requires-Dist: tox >=3.24 ; extra == 'testing'
